README.md
setup.py
jingd/__init__.py
jingd/block.py
jingd/reset.py
jingd/unlock.py
jingd/usermod.py
jingd.egg-info/PKG-INFO
jingd.egg-info/SOURCES.txt
jingd.egg-info/dependency_links.txt
jingd.egg-info/entry_points.txt
jingd.egg-info/requires.txt
jingd.egg-info/top_level.txt
jingd/admin/__init__.py
jingd/admin/admin.py