Metadata-Version: 1.0
Name: jingd
Version: 0.0.3
Summary: jingd auth Service Library
Home-page: https://github.com/
Author: wangzhihao.sh
Author-email: zhouheng@gene.ac
License: MIT
Keywords: jingd
Platform: UNKNOWN
